LICENSE
README.md
setup.cfg
setup.py
errors/__init__.py
errors/api_errors.py
errors/library_errors.py
lazarus_ai/__init__.py
lazarus_ai/forms.py
lazarus_ai/lazarus_auth.py
lazarus_ai/rikai.py
lazarus_ai.egg-info/PKG-INFO
lazarus_ai.egg-info/SOURCES.txt
lazarus_ai.egg-info/dependency_links.txt
lazarus_ai.egg-info/requires.txt
lazarus_ai.egg-info/top_level.txt
utils/__init__.py
utils/args_validation.py
utils/error_handling.py
utils/input_types.py
utils/metrics.py