Metadata-Version: 2.1
Name: lazarus-ai
Version: 1.0.1
Summary: Lazarus AI Python Library
Home-page: https://www.lazarusforms.com/
Download-URL: https://github.com/Lazarus-AI/lazarus-ai-python/archive/refs/tags/v1.0.1.tar.gz
Author: Caroline Abel, KK Barrows, Alvin Xie
Author-email: caroline@lazarus.enterprises, kathleen@lazarus.enterprises, alvin@lazarus.enterprises
License: MIT
Project-URL: Bug Tracker, https://github.com/Lazarus-AI/lazarus-ai-python/issues
Project-URL: Documentation, https://lazarus.stoplight.io/docs/lazarus-forms/welcome
Project-URL: Source Code, https://github.com/Lazarus-AI/lazarus-ai-python
Classifier: License :: OSI Approved :: MIT License
Classifier: Programming Language :: Python :: 3
Classifier: Programming Language :: Python :: 3.7
License-File: LICENSE
Requires-Dist: requests
Requires-Dist: stringcase
